accelerate/__init__.py
accelerate/accelerator.py
accelerate/big_modeling.py
accelerate/checkpointing.py
accelerate/data_loader.py
accelerate/hooks.py
accelerate/inference.py
accelerate/launchers.py
accelerate/local_sgd.py
accelerate/logging.py
accelerate/memory_utils.py
accelerate/optimizer.py
accelerate/scheduler.py
accelerate/state.py
accelerate/tracking.py
accelerate/commands/__init__.py
accelerate/commands/accelerate_cli.py
accelerate/commands/env.py
accelerate/commands/estimate.py
accelerate/commands/launch.py
accelerate/commands/merge.py
accelerate/commands/test.py
accelerate/commands/to_fsdp2.py
accelerate/commands/tpu.py
accelerate/commands/utils.py
accelerate/commands/config/__init__.py
accelerate/commands/config/cluster.py
accelerate/commands/config/config.py
accelerate/commands/config/config_args.py
accelerate/commands/config/config_utils.py
accelerate/commands/config/default.py
accelerate/commands/config/sagemaker.py
accelerate/commands/config/update.py
accelerate/commands/menu/__init__.py
accelerate/commands/menu/cursor.py
accelerate/commands/menu/helpers.py
accelerate/commands/menu/input.py
accelerate/commands/menu/keymap.py
accelerate/commands/menu/selection_menu.py
accelerate/test_utils/__init__.py
accelerate/test_utils/examples.py
accelerate/test_utils/testing.py
accelerate/test_utils/training.py
accelerate/test_utils/scripts/__init__.py
accelerate/test_utils/scripts/test_cli.py
accelerate/test_utils/scripts/test_ddp_comm_hook.py
accelerate/test_utils/scripts/test_distributed_data_loop.py
accelerate/test_utils/scripts/test_merge_weights.py
accelerate/test_utils/scripts/test_notebook.py
accelerate/test_utils/scripts/test_ops.py
accelerate/test_utils/scripts/test_script.py
accelerate/test_utils/scripts/test_sync.py
accelerate/test_utils/scripts/external_deps/__init__.py
accelerate/test_utils/scripts/external_deps/test_checkpointing.py
accelerate/test_utils/scripts/external_deps/test_ds_multiple_model.py
accelerate-1.8.0.dist-info/licenses/LICENSE
accelerate-1.8.0.dist-info/METADATA
accelerate-1.8.0.dist-info/WHEEL
accelerate-1.8.0.dist-info/entry_points.txt
accelerate-1.8.0.dist-info/top_level.txt
accelerate-1.8.0.dist-info/RECORD
