Metadata-Version: 2.4
Name: accelerate
Version: 1.8.0
Summary: Accelerate
Home-page: https://github.com/huggingface/accelerate
Author: The HuggingFace team
Author-email: zach.mueller@huggingface.co
License: Apache
Keywords: deep learning
Classifier: Development Status :: 5 - Production/Stable
Classifier: Intended Audience :: Developers
Classifier: Intended Audience :: Education
Classifier: Intended Audience :: Science/Research
Classifier: License :: OSI Approved :: Apache Software License
Classifier: Operating System :: OS Independent
Classifier: Programming Language :: Python :: 3
Classifier: Programming Language :: Python :: 3.9
Classifier: Topic :: Scientific/Engineering :: Artificial Intelligence
Requires-Python: >=3.9.0
License-File: LICENSE
Requires-Dist: numpy<3.0.0,>=1.17
Requires-Dist: packaging>=20.0
Requires-Dist: psutil
Requires-Dist: pyyaml
Requires-Dist: torch>=2.0.0
Requires-Dist: huggingface_hub>=0.21.0
Requires-Dist: safetensors>=0.4.3
Provides-Extra: quality
Requires-Dist: black~=23.1; extra == "quality"
Requires-Dist: hf-doc-builder>=0.3.0; extra == "quality"
Requires-Dist: ruff~=0.11.2; extra == "quality"
Provides-Extra: docs
Provides-Extra: test-prod
Requires-Dist: pytest<=8.0.0,>=7.2.0; extra == "test-prod"
Requires-Dist: pytest-xdist; extra == "test-prod"
Requires-Dist: pytest-subtests; extra == "test-prod"
Requires-Dist: parameterized; extra == "test-prod"
Requires-Dist: pytest-order; extra == "test-prod"
Provides-Extra: test-dev
Requires-Dist: datasets; extra == "test-dev"
Requires-Dist: diffusers; extra == "test-dev"
Requires-Dist: evaluate; extra == "test-dev"
Requires-Dist: torchdata>=0.8.0; extra == "test-dev"
Requires-Dist: torchpippy>=0.2.0; extra == "test-dev"
Requires-Dist: transformers; extra == "test-dev"
Requires-Dist: scipy; extra == "test-dev"
Requires-Dist: scikit-learn; extra == "test-dev"
Requires-Dist: tqdm; extra == "test-dev"
Requires-Dist: bitsandbytes; extra == "test-dev"
Requires-Dist: timm; extra == "test-dev"
Provides-Extra: testing
Requires-Dist: pytest<=8.0.0,>=7.2.0; extra == "testing"
Requires-Dist: pytest-xdist; extra == "testing"
Requires-Dist: pytest-subtests; extra == "testing"
Requires-Dist: parameterized; extra == "testing"
Requires-Dist: pytest-order; extra == "testing"
Requires-Dist: datasets; extra == "testing"
Requires-Dist: diffusers; extra == "testing"
Requires-Dist: evaluate; extra == "testing"
Requires-Dist: torchdata>=0.8.0; extra == "testing"
Requires-Dist: torchpippy>=0.2.0; extra == "testing"
Requires-Dist: transformers; extra == "testing"
Requires-Dist: scipy; extra == "testing"
Requires-Dist: scikit-learn; extra == "testing"
Requires-Dist: tqdm; extra == "testing"
Requires-Dist: bitsandbytes; extra == "testing"
Requires-Dist: timm; extra == "testing"
Provides-Extra: deepspeed
Requires-Dist: deepspeed; extra == "deepspeed"
Provides-Extra: rich
Requires-Dist: rich; extra == "rich"
Provides-Extra: test-fp8
Requires-Dist: torchao; extra == "test-fp8"
Provides-Extra: test-trackers
Requires-Dist: wandb; extra == "test-trackers"
Requires-Dist: comet-ml; extra == "test-trackers"
Requires-Dist: tensorboard; extra == "test-trackers"
Requires-Dist: dvclive; extra == "test-trackers"
Requires-Dist: mlflow; extra == "test-trackers"
Requires-Dist: matplotlib; extra == "test-trackers"
Requires-Dist: swanlab; extra == "test-trackers"
Provides-Extra: dev
Requires-Dist: black~=23.1; extra == "dev"
Requires-Dist: hf-doc-builder>=0.3.0; extra == "dev"
Requires-Dist: ruff~=0.11.2; extra == "dev"
Requires-Dist: pytest<=8.0.0,>=7.2.0; extra == "dev"
Requires-Dist: pytest-xdist; extra == "dev"
Requires-Dist: pytest-subtests; extra == "dev"
Requires-Dist: parameterized; extra == "dev"
Requires-Dist: pytest-order; extra == "dev"
Requires-Dist: datasets; extra == "dev"
Requires-Dist: diffusers; extra == "dev"
Requires-Dist: evaluate; extra == "dev"
Requires-Dist: torchdata>=0.8.0; extra == "dev"
Requires-Dist: torchpippy>=0.2.0; extra == "dev"
Requires-Dist: transformers; extra == "dev"
Requires-Dist: scipy; extra == "dev"
Requires-Dist: scikit-learn; extra == "dev"
Requires-Dist: tqdm; extra == "dev"
Requires-Dist: bitsandbytes; extra == "dev"
Requires-Dist: timm; extra == "dev"
Requires-Dist: rich; extra == "dev"
Provides-Extra: sagemaker
Requires-Dist: sagemaker; extra == "sagemaker"
Dynamic: author
Dynamic: author-email
Dynamic: classifier
Dynamic: description
Dynamic: description-content-type
Dynamic: home-page
Dynamic: keywords
Dynamic: license
Dynamic: license-file
Dynamic: provides-extra
Dynamic: requires-dist
Dynamic: requires-python
Dynamic: summary
